tests/__init__.py
tests/test_time_boss.py
time_boss/__init__.py
time_boss/time_boss.py
TimeBoss-0.1.3.dist-info/LICENSE
TimeBoss-0.1.3.dist-info/METADATA
TimeBoss-0.1.3.dist-info/WHEEL
TimeBoss-0.1.3.dist-info/top_level.txt
TimeBoss-0.1.3.dist-info/RECORD
