Metadata-Version: 2.1
Name: TimeBoss
Version: 0.1.3
Summary: A lightweight python timing class
Home-page: https://github.com/chrhck/TimeBoss
Author: Christian Haack
Author-email: chr.hck@gmail.com
License: UNKNOWN
Platform: UNKNOWN
Classifier: Programming Language :: Python :: 3
Classifier: License :: OSI Approved :: GNU General Public License v3 (GPLv3)
Classifier: Operating System :: OS Independent
Requires-Python: >=3.6
Requires-Dist: numpy
